PyQt5-stubs/Qt3DAnimation.pyi
PyQt5-stubs/Qt3DCore.pyi
PyQt5-stubs/Qt3DExtras.pyi
PyQt5-stubs/Qt3DInput.pyi
PyQt5-stubs/Qt3DLogic.pyi
PyQt5-stubs/Qt3DRender.pyi
PyQt5-stubs/QtBluetooth.pyi
PyQt5-stubs/QtChart.pyi
PyQt5-stubs/QtCore.pyi
PyQt5-stubs/QtDBus.pyi
PyQt5-stubs/QtDataVisualization.pyi
PyQt5-stubs/QtDesigner.pyi
PyQt5-stubs/QtGui.pyi
PyQt5-stubs/QtHelp.pyi
PyQt5-stubs/QtLocation.pyi
PyQt5-stubs/QtMultimedia.pyi
PyQt5-stubs/QtMultimediaWidgets.pyi
PyQt5-stubs/QtNetwork.pyi
PyQt5-stubs/QtNetworkAuth.pyi
PyQt5-stubs/QtNfc.pyi
PyQt5-stubs/QtOpenGL.pyi
PyQt5-stubs/QtPositioning.pyi
PyQt5-stubs/QtPrintSupport.pyi
PyQt5-stubs/QtPurchasing.pyi
PyQt5-stubs/QtQml.pyi
PyQt5-stubs/QtQuick.pyi
PyQt5-stubs/QtQuickWidgets.pyi
PyQt5-stubs/QtRemoteObjects.pyi
PyQt5-stubs/QtSensors.pyi
PyQt5-stubs/QtSerialPort.pyi
PyQt5-stubs/QtSql.pyi
PyQt5-stubs/QtSvg.pyi
PyQt5-stubs/QtTest.pyi
PyQt5-stubs/QtWebChannel.pyi
PyQt5-stubs/QtWebEngine.pyi
PyQt5-stubs/QtWebEngineCore.pyi
PyQt5-stubs/QtWebEngineWidgets.pyi
PyQt5-stubs/QtWebKit.pyi
PyQt5-stubs/QtWebKitWidgets.pyi
PyQt5-stubs/QtWebSockets.pyi
PyQt5-stubs/QtWidgets.pyi
PyQt5-stubs/QtX11Extras.pyi
PyQt5-stubs/QtXml.pyi
PyQt5-stubs/QtXmlPatterns.pyi
PyQt5-stubs/__init__.pyi
PyQt5-stubs/sip.pyi
PyQt5_stubs-5.15.6.0.dist-info/LICENSE
PyQt5_stubs-5.15.6.0.dist-info/METADATA
PyQt5_stubs-5.15.6.0.dist-info/WHEEL
PyQt5_stubs-5.15.6.0.dist-info/top_level.txt
PyQt5_stubs-5.15.6.0.dist-info/RECORD
