Metadata-Version: 2.1
Name: PyQt5-stubs
Version: 5.15.6.0
Summary: PEP561 stub files for the PyQt5 framework
Home-page: https://github.com/python-qt-tools/PyQt5-stubs
Author: Stefan Lehmann
Maintainer: Kyle Altendorf, Bryce Beagle, Florian Bruhin, Philippe Fremy
Maintainer-email: phil.fremy@free.fr
License: UNKNOWN
Platform: UNKNOWN
Classifier: Development Status :: 5 - Production/Stable
Classifier: Intended Audience :: Developers
Classifier: License :: OSI Approved :: GNU General Public License v3 (GPLv3)
Classifier: Programming Language :: Python :: 3
Classifier: Topic :: Software Development
Requires-Python: >= 3.5
Provides-Extra: dev
License-File: LICENSE
